{"session_uid":"1028832261159831181","start_time":"2026-04-29T19:39:03.428759+00:00","track":"Imola","session_type":"Unknown(15)","weather":"Light Cloud","total_samples":1,"last_updated":"2026-04-29T19:39:03.447371+00:00","samples":[{"t":661.237,"tel":{"speed":73,"throttle":1.0,"brake":0.0,"steer":-0.1,"gear":2,"rpm":6662,"drs":0,"engine_temp":120,"brakes_temp":[981,978,1001,1000],"tyres_inner":[90,90,90,90],"tyres_surface":[67,66,65,61],"tyres_pressure":[21.3,21.3,24.2,24.2]},"mot":{"x":0.0,"z":0.0,"g_lat":0.0,"g_lon":0.0},"lap":{"pos":99,"lap_num":3,"lap_time_ms":0,"last_lap_ms":131072,"sector":137,"lap_dist":0},"status":{"fuel":10.64,"fuel_laps":5.8,"ers_pct":100,"ers_mode":1,"tyre":"Soft","tyre_age":4}}]}